{
  "sumneko-lua.enableNvimLuaDev": true,
  "languageserver": {
    "ccls": {
      "command": "ccls",
      "filetypes": ["c", "cpp", "objc", "objcpp"],
      "trace.server": "verbose",
      "initializationOptions": {
        "cacheDirectory": "/tmp/ccls"
      }
    },
    "golang": {
      "command": "gopls",
      "rootPatterns": ["go.mod"],
      "filetypes": ["go"]
    },
    "dockercompose": {
      "command": "docker-compose-langserver",
      "args": ["--stdio"],
      "filetypes": ["dockercompose"],
      "rootPatterns": [".git", ".env", "docker-compose.yml", "compose.yml"]
    },
    "dockerfile": {
      "command": "docker-langserver",
      "filetypes": ["dockerfile"],
      "args": ["--stdio"]
    }
  }
}
